grafanarmadillo/__init__.py
grafanarmadillo/alerter.py
grafanarmadillo/bulk.py
grafanarmadillo/cmd.py
grafanarmadillo/dashboarder.py
grafanarmadillo/find.py
grafanarmadillo/flow.py
grafanarmadillo/migrate.py
grafanarmadillo/paths.py
grafanarmadillo/templator.py
grafanarmadillo/types.py
grafanarmadillo/util.py
grafanarmadillo-0.9.0.dist-info/METADATA
grafanarmadillo-0.9.0.dist-info/WHEEL
grafanarmadillo-0.9.0.dist-info/entry_points.txt
grafanarmadillo-0.9.0.dist-info/top_level.txt
grafanarmadillo-0.9.0.dist-info/RECORD
