Metadata-Version: 2.2
Name: grafanarmadillo
Version: 0.9.0
Summary: Simplify interacting with Grafana, with a focus on templating dashboards and alerts
Author: lilatomic
Maintainer: lilatomic
Project-URL: Homepage, https://github.com/lilatomic/grafanarmadillo
Project-URL: Repository, https://github.com/lilatomic/grafanarmadillo.git
Project-URL: Documentation, https://grafanarmadillo.readthedocs.io/en/latest/
Project-URL: Changelog, https://github.com/lilatomic/grafanarmadillo/blob/main/docs/CHANGELOG.rst
Project-URL: Issues, https://github.com/lilatomic/grafanarmadillo/issues
Classifier: Development Status :: 4 - Beta
Classifier: Programming Language :: Python :: 3.8
Classifier: Programming Language :: Python :: 3.9
Classifier: Programming Language :: Python :: 3.10
Classifier: Programming Language :: Python :: 3.11
Classifier: Programming Language :: Python :: 3.12
Classifier: Programming Language :: Python :: 3.13
Requires-Python: <4,>=3.8
Requires-Dist: grafana-client>=3.0
Provides-Extra: cli
Requires-Dist: click>=8; extra == "cli"
Provides-Extra: migrate
Requires-Dist: docker>=6; extra == "migrate"
